<mujoco>
  <actuator>
    <general name="LD_L1_r" class="muscle" tendon="LD_L1_r_tendon" lengthrange="0.238419 0.570316" gainprm="0.75 1.05 90.3992" biasprm="0.75 1.05 90.3992" />
    <general name="LD_L2_r" class="muscle" tendon="LD_L2_r_tendon" lengthrange="0.256534 0.613647" gainprm="0.75 1.05 84.5399" biasprm="0.75 1.05 84.5399" />
    <general name="LD_L3_r" class="muscle" tendon="LD_L3_r_tendon" lengthrange="0.271513 0.649478" gainprm="0.75 1.05 104.518" biasprm="0.75 1.05 104.518" />
    <general name="LD_L4_r" class="muscle" tendon="LD_L4_r_tendon" lengthrange="0.283672 0.678564" gainprm="0.75 1.05 100.728" biasprm="0.75 1.05 100.728" />
    <general name="LD_L5_r" class="muscle" tendon="LD_L5_r_tendon" lengthrange="0.29438 0.711729" gainprm="0.75 1.05 101.688" biasprm="0.75 1.05 101.688" />
    <general name="LD_T12_r" class="muscle" tendon="LD_T12_r_tendon" lengthrange="0.222824 0.538726" gainprm="0.75 1.05 53.7059" biasprm="0.75 1.05 53.7059" />
    <general name="LD_T11_r" class="muscle" tendon="LD_T11_r_tendon" lengthrange="0.208147 0.503241" gainprm="0.75 1.05 62.9177" biasprm="0.75 1.05 62.9177" />
    <general name="LD_T10_r" class="muscle" tendon="LD_T10_r_tendon" lengthrange="0.191223 0.482517" gainprm="0.75 1.05 64.479" biasprm="0.75 1.05 64.479" />
    <general name="LD_T9_r" class="muscle" tendon="LD_T9_r_tendon" lengthrange="0.167304 0.42216" gainprm="0.75 1.05 40.6246" biasprm="0.75 1.05 40.6246" />
    <general name="LD_T8_r" class="muscle" tendon="LD_T8_r_tendon" lengthrange="0.167045 0.403868" gainprm="0.75 1.05 40.7947" biasprm="0.75 1.05 40.7947" />
    <general name="LD_T7_r" class="muscle" tendon="LD_T7_r_tendon" lengthrange="0.15728 0.38026" gainprm="0.75 1.05 37.075" biasprm="0.75 1.05 37.075" />
    <general name="LD_R12_r" class="muscle" tendon="LD_R12_r_tendon" lengthrange="0.193022 0.466673" gainprm="0.75 1.05 42.9003" biasprm="0.75 1.05 42.9003" />
    <general name="LD_R11_r" class="muscle" tendon="LD_R11_r_tendon" lengthrange="0.168615 0.407664" gainprm="0.75 1.05 63.3336" biasprm="0.75 1.05 63.3336" />
    <general name="LD_IL_r" class="muscle" tendon="LD_IL_r_tendon" lengthrange="0.252616 0.717639" gainprm="0.75 1.05 65.3663" biasprm="0.75 1.05 65.3663" />
    <general name="DELT1_r" class="muscle" tendon="DELT1_r_tendon" lengthrange="0.138247 0.22874" gainprm="0.75 1.05 1218.9" biasprm="0.75 1.05 1218.9" />
    <general name="DELT2_r" class="muscle" tendon="DELT2_r_tendon" lengthrange="0.161563 0.26569" gainprm="0.75 1.05 1103.5" biasprm="0.75 1.05 1103.5" />
    <general name="DELT3_r" class="muscle" tendon="DELT3_r_tendon" lengthrange="0.103005 0.233014" gainprm="0.75 1.05 201.6" biasprm="0.75 1.05 201.6" />
    <general name="SUPSP_r" class="muscle" tendon="SUPSP_r_tendon" lengthrange="0.0733458 0.141037" gainprm="0.75 1.05 499.2" biasprm="0.75 1.05 499.2" />
    <general name="INFSP_r" class="muscle" tendon="INFSP_r_tendon" lengthrange="0.0664933 0.13788" gainprm="0.75 1.05 1075.8" biasprm="0.75 1.05 1075.8" />
    <general name="SUBSC_r" class="muscle" tendon="SUBSC_r_tendon" lengthrange="0.0740175 0.156053" gainprm="0.75 1.05 1306.9" biasprm="0.75 1.05 1306.9" />
    <general name="TMIN_r" class="muscle" tendon="TMIN_r_tendon" lengthrange="0.105147 0.172841" gainprm="0.75 1.05 269.5" biasprm="0.75 1.05 269.5" />
    <general name="TMAJ_r" class="muscle" tendon="TMAJ_r_tendon" lengthrange="0.0980544 0.254163" gainprm="0.75 1.05 144" biasprm="0.75 1.05 144" />
    <general name="PECM1_r" class="muscle" tendon="PECM1_r_tendon" lengthrange="0.0717495 0.209649" gainprm="0.75 1.05 444.3" biasprm="0.75 1.05 444.3" />
    <general name="PECM2_r" class="muscle" tendon="PECM2_r_tendon" lengthrange="0.151241 0.275724" gainprm="0.75 1.05 658.3" biasprm="0.75 1.05 658.3" />
    <general name="PECM3_r" class="muscle" tendon="PECM3_r_tendon" lengthrange="0.194762 0.320285" gainprm="0.75 1.05 498.1" biasprm="0.75 1.05 498.1" />
    <general name="CORB_r" class="muscle" tendon="CORB_r_tendon" lengthrange="0.138521 0.221563" gainprm="0.75 1.05 208.2" biasprm="0.75 1.05 208.2" />
    <general name="TRIlong_r" class="muscle" tendon="TRIlong_r_tendon" lengthrange="0.208536 0.339608" gainprm="0.75 1.05 771.8" biasprm="0.75 1.05 771.8" />
    <general name="TRIlat_r" class="muscle" tendon="TRIlat_r_tendon" lengthrange="0.154199 0.266598" gainprm="0.75 1.05 717.5" biasprm="0.75 1.05 717.5" />
    <general name="TRImed_r" class="muscle" tendon="TRImed_r_tendon" lengthrange="0.146999 0.259398" gainprm="0.75 1.05 717.5" biasprm="0.75 1.05 717.5" />
    <general name="ANC_r" class="muscle" tendon="ANC_r_tendon" lengthrange="0.0315 0.0584999" gainprm="0.75 1.05 283.2" biasprm="0.75 1.05 283.2" />
    <general name="SUP_r" class="muscle" tendon="SUP_r_tendon" lengthrange="0.0445 0.0774999" gainprm="0.75 1.05 379.6" biasprm="0.75 1.05 379.6" />
    <general name="BIClong_r" class="muscle" tendon="BIClong_r_tendon" lengthrange="0.33015 0.44585" gainprm="0.75 1.05 525.1" biasprm="0.75 1.05 525.1" />
    <general name="BICshort_r" class="muscle" tendon="BICshort_r_tendon" lengthrange="0.25835 0.39045" gainprm="0.75 1.05 316.8" biasprm="0.75 1.05 316.8" />
    <general name="BRA_r" class="muscle" tendon="BRA_r_tendon" lengthrange="0.0964 0.1822" gainprm="0.75 1.05 1177.37" biasprm="0.75 1.05 1177.37" />
    <general name="BRD_r" class="muscle" tendon="BRD_r_tendon" lengthrange="0.2193 0.3919" gainprm="0.75 1.05 276" biasprm="0.75 1.05 276" />
    <general name="ECRL_r" class="muscle" tendon="ECRL_r_tendon" lengthrange="0.2845 0.3655" gainprm="0.75 1.05 337.3" biasprm="0.75 1.05 337.3" />
    <general name="ECRB_r" class="muscle" tendon="ECRB_r_tendon" lengthrange="0.25119 0.30897" gainprm="0.75 1.05 252.5" biasprm="0.75 1.05 252.5" />
    <general name="ECU_r" class="muscle" tendon="ECU_r_tendon" lengthrange="0.259524 0.321573" gainprm="0.75 1.05 192.9" biasprm="0.75 1.05 192.9" />
    <general name="FCR_r" class="muscle" tendon="FCR_r_tendon" lengthrange="0.275357 0.338071" gainprm="0.75 1.05 407.9" biasprm="0.75 1.05 407.9" />
    <general name="FCU_r" class="muscle" tendon="FCU_r_tendon" lengthrange="0.289894 0.339681" gainprm="0.75 1.05 479.8" biasprm="0.75 1.05 479.8" />
    <general name="PL_r" class="muscle" tendon="PL_r_tendon" lengthrange="0.301222 0.364867" gainprm="0.75 1.05 101" biasprm="0.75 1.05 101" />
    <general name="PT_r" class="muscle" tendon="PT_r_tendon" lengthrange="0.122226 0.170679" gainprm="0.75 1.05 557.2" biasprm="0.75 1.05 557.2" />
    <general name="PQ_r" class="muscle" tendon="PQ_r_tendon" lengthrange="0.0188857 0.0466573" gainprm="0.75 1.05 284.7" biasprm="0.75 1.05 284.7" />
    <general name="FDSL_r" class="muscle" tendon="FDSL_r_tendon" lengthrange="0.374252 0.425556" gainprm="0.75 1.05 75.3" biasprm="0.75 1.05 75.3" />
    <general name="FDSR_r" class="muscle" tendon="FDSR_r_tendon" lengthrange="0.39471 0.468131" gainprm="0.75 1.05 171.2" biasprm="0.75 1.05 171.2" />
    <general name="FDSM_r" class="muscle" tendon="FDSM_r_tendon" lengthrange="0.352171 0.426512" gainprm="0.75 1.05 258.8" biasprm="0.75 1.05 258.8" />
    <general name="FDSI_r" class="muscle" tendon="FDSI_r_tendon" lengthrange="0.316521 0.399564" gainprm="0.75 1.05 162.5" biasprm="0.75 1.05 162.5" />
    <general name="FDPL_r" class="muscle" tendon="FDPL_r_tendon" lengthrange="0.348985 0.423157" gainprm="0.75 1.05 236.8" biasprm="0.75 1.05 236.8" />
    <general name="FDPR_r" class="muscle" tendon="FDPR_r_tendon" lengthrange="0.361103 0.440308" gainprm="0.75 1.05 172.9" biasprm="0.75 1.05 172.9" />
    <general name="FDPM_r" class="muscle" tendon="FDPM_r_tendon" lengthrange="0.374521 0.457564" gainprm="0.75 1.05 212.4" biasprm="0.75 1.05 212.4" />
    <general name="FDPI_r" class="muscle" tendon="FDPI_r_tendon" lengthrange="0.368671 0.443012" gainprm="0.75 1.05 197.3" biasprm="0.75 1.05 197.3" />
    <general name="EDCL_r" class="muscle" tendon="EDCL_r_tendon" lengthrange="0.36748 0.432441" gainprm="0.75 1.05 39.4" biasprm="0.75 1.05 39.4" />
    <general name="EDCR_r" class="muscle" tendon="EDCR_r_tendon" lengthrange="0.396257 0.458771" gainprm="0.75 1.05 109.2" biasprm="0.75 1.05 109.2" />
    <general name="EDCM_r" class="muscle" tendon="EDCM_r_tendon" lengthrange="0.40115 0.473451" gainprm="0.75 1.05 94.4" biasprm="0.75 1.05 94.4" />
    <general name="EDCI_r" class="muscle" tendon="EDCI_r_tendon" lengthrange="0.399952 0.469856" gainprm="0.75 1.05 48.8" biasprm="0.75 1.05 48.8" />
    <general name="EDM_r" class="muscle" tendon="EDM_r_tendon" lengthrange="0.368704 0.436111" gainprm="0.75 1.05 72.4" biasprm="0.75 1.05 72.4" />
    <general name="EIP_r" class="muscle" tendon="EIP_r_tendon" lengthrange="0.239289 0.297866" gainprm="0.75 1.05 47.3" biasprm="0.75 1.05 47.3" />
    <general name="EPL_r" class="muscle" tendon="EPL_r_tendon" lengthrange="0.257352 0.311056" gainprm="0.75 1.05 88.3" biasprm="0.75 1.05 88.3" />
    <general name="EPB_r" class="muscle" tendon="EPB_r_tendon" lengthrange="0.148998 0.215995" gainprm="0.75 1.05 46" biasprm="0.75 1.05 46" />
    <general name="FPL_r" class="muscle" tendon="FPL_r_tendon" lengthrange="0.224394 0.279183" gainprm="0.75 1.05 201" biasprm="0.75 1.05 201" />
    <general name="APL_r" class="muscle" tendon="APL_r_tendon" lengthrange="0.164803 0.235409" gainprm="0.75 1.05 116.7" biasprm="0.75 1.05 116.7" />
  </actuator>
</mujoco>